examtool/api/__init__.py
examtool/api/assemble_export.py
examtool/api/convert.py
examtool/api/database.py
examtool/api/download.py
examtool/api/email.py
examtool/api/extract_questions.py
examtool/api/gen_latex.py
examtool/api/grade.py
examtool/api/gradescope_autograde.py
examtool/api/gradescope_upload.py
examtool/api/render_html_export.py
examtool/api/render_pdf_export.py
examtool/api/scramble.py
examtool/api/server_delegate.py
examtool/api/substitution_finder.py
examtool/api/substitutions.py
examtool/api/utils.py
examtool/api/watermark_decoder.py
examtool/api/watermarks.py
examtool/api/css/style.css
examtool/api/tex/prefix.tex
examtool/api/tex/suffix.tex
examtool/cli/__init__.py
examtool/cli/__main__.py
examtool/cli/cheaters.py
examtool/cli/check_dupes.py
examtool/cli/compile.py
examtool/cli/compile_all.py
examtool/cli/deploy.py
examtool/cli/download.py
examtool/cli/find_errors.py
examtool/cli/generate_roster_csv.py
examtool/cli/gradescope_autograde.py
examtool/cli/gradescope_upload.py
examtool/cli/identify_keyword.py
examtool/cli/identify_watermark.py
examtool/cli/kdf.py
examtool/cli/login.py
examtool/cli/loginas.py
examtool/cli/logs.py
examtool/cli/save_logs.py
examtool/cli/send.py
examtool/cli/substitutions.py
examtool/cli/utils.py
examtool/common/__init__.py
examtool/common/cli_utils.py
examtool/common/course_config.py
examtool/common/db.py
examtool/common/hash_utils.py
examtool/common/html.py
examtool/common/jobs.py
examtool/common/oauth_client.py
examtool/common/permissions.py
examtool/common/secrets.py
examtool/common/shell_utils.py
examtool/common/url_for.py
examtool/common/rpc/__init__.py
examtool/common/rpc/ag_master.py
examtool/common/rpc/ag_worker.py
examtool/common/rpc/auth.py
examtool/common/rpc/auth_utils.py
examtool/common/rpc/buildserver.py
examtool/common/rpc/buildserver_hosted_worker.py
examtool/common/rpc/code.py
examtool/common/rpc/domains.py
examtool/common/rpc/hosted.py
examtool/common/rpc/howamidoing.py
examtool/common/rpc/indexer.py
examtool-2.2.45.dist-info/METADATA
examtool-2.2.45.dist-info/WHEEL
examtool-2.2.45.dist-info/entry_points.txt
examtool-2.2.45.dist-info/top_level.txt
examtool-2.2.45.dist-info/RECORD
