Metadata-Version: 2.1
Name: examtool
Version: 2.2.45
Summary: UNKNOWN
Home-page: UNKNOWN
Author: Rahul Arya
Author-email: rahularya@berkeley.edu
License: MIT
Platform: UNKNOWN
Requires-Python: >=3.7
Requires-Dist: cryptography
Provides-Extra: admin
Requires-Dist: pytz ; extra == 'admin'
Requires-Dist: requests ; extra == 'admin'
Requires-Dist: pypandoc ; extra == 'admin'
Requires-Dist: google-cloud-firestore ; extra == 'admin'
Requires-Dist: google-auth ; extra == 'admin'
Requires-Dist: sendgrid ; extra == 'admin'
Provides-Extra: cli
Requires-Dist: click ; extra == 'cli'
Requires-Dist: pikepdf ; extra == 'cli'
Requires-Dist: pytz ; extra == 'cli'
Requires-Dist: requests ; extra == 'cli'
Requires-Dist: fpdf ; extra == 'cli'
Requires-Dist: pypandoc ; extra == 'cli'
Requires-Dist: sendgrid ; extra == 'cli'
Requires-Dist: func-timeout ; extra == 'cli'
Requires-Dist: fullGSapi >=1.3.7 ; extra == 'cli'
Requires-Dist: tqdm ; extra == 'cli'
Requires-Dist: numpy ; extra == 'cli'
Requires-Dist: opencv-python ; extra == 'cli'
Requires-Dist: pdfkit ; extra == 'cli'
